{
    "items":
    [
        {
            "nameFruit": "Quinoa fruit salad",
            "price": 10.000,
            "ingredients": "Red Quinoa, Lime, Honey, Blueberries, Strawberries, Mango, Fresh mint.",
            "description": "If you are looking for a new fruit salad to eat today, quinoa is the perfect brunch for you. make",
            "image": "./quinoa.svg"
        },

        {
            "nameFruit": "Tropical fruit salad",
            "price": 10.000,
            "ingredients": "Lorem Ipsum is simply dummy.",
            "description": "Lorem Ipsum is simply dummy text of the printing and typesetting industry.",
            "image": "./tropical.svg"
        },

        {
            "nameFruit": "Melon fruit salad",
            "price": 10.000,
            "ingredients": "Lorem Ipsum is simply dummy.",
            "description": "Lorem Ipsum is simply dummy text of the printing and typesetting industry.",
            "image": "./melon.svg"
        },

        {
            "nameFruit": "Berry mango combo",
            "price": 8.000,
            "ingredients": "Lorem Ipsum is simply dummy.",
            "description": "Lorem Ipsum is simply dummy text of the printing and typesetting industry.",
            "image": "./berryMango.svg"
        },

        {
            "nameFruit": "Honey lime combo",
            "price": 2.000,
            "ingredients": "Lorem Ipsum is simply dummy.",
            "description": "Lorem Ipsum is simply dummy text of the printing and typesetting industry.",
            "image": "./honeyLime.svg"
        }
    ]
}